langchain_sgframework/__init__.py
langchain_sgframework/logging.py
lanchain_sgframework-0.1.6.dist-info/METADATA
lanchain_sgframework-0.1.6.dist-info/WHEEL
lanchain_sgframework-0.1.6.dist-info/top_level.txt
lanchain_sgframework-0.1.6.dist-info/RECORD
