Metadata-Version: 2.4
Name: lanchain-sgframework
Version: 0.1.6
Summary: LangChain Helper Library
Requires-Python: >=3.13
Requires-Dist: langchain>=0.3.27
Requires-Dist: langchain-mcp-adapters>=0.1.9
